pryanda_client/__init__.py
pryanda_client/core.py
pryanda_client-0.1.0.dist-info/licenses/LICENSE
pryanda_client-0.1.0.dist-info/METADATA
pryanda_client-0.1.0.dist-info/WHEEL
pryanda_client-0.1.0.dist-info/top_level.txt
pryanda_client-0.1.0.dist-info/RECORD
